html_matcher/__init__.py
html_matcher/export.py
html_matcher/main.py
html_matcher/ms.py
html_matcher/similarity.py
html_matcher/style.py
html_matcher/ted.py
html_matcher/utils.py
html_matcher-0.1.1.dist-info/LICENSE
html_matcher-0.1.1.dist-info/METADATA
html_matcher-0.1.1.dist-info/WHEEL
html_matcher-0.1.1.dist-info/top_level.txt
html_matcher-0.1.1.dist-info/RECORD
